Workbook

Sheet README
B7: PAYROLL & EMPLOYEE COST ANALYSIS MODEL
B9: Purpose | C9: Finance-focused model for payroll, employee-cost analysis, budgeting and workforce scenarios.
B10: Data | C10: 100 simulated/fabricated employee records for academic and confidentiality purposes.
B11: Confidentiality | C11: No actual employee-level company payroll data is used.
B12: Tools | C12: Microsoft Excel formulas, departmental analysis, variance analysis, scenario analysis and dashboard.
B13: Workbook flow | C13: Employee_Data → Payroll_Calculation → Department_Cost_Analysis → Budget_vs_Actual → Scenario_Analysis → Dashboard → Management_Insights

Sheet Employee_Data
A1: Employee ID | B1: Department | C1: Designation | D1: Location | E1: Basic Salary | F1: HRA | G1: Allowances | H1: Incentive | I1: Overtime | J1: Employee PF | K1: Tax | L1: Employer Contribution | M1: Gross Salary | N1: Net Salary | O1: Employer Cost
A2: EMP1001 | B2: HR | C2: HR Executive | D2: Gurugram | E2: 47174 | F2: 10734 | G2: 4219 | H2: 2625 | I2: 697 | J2: 5661 | K2: 3364 | L2: 5661 | M2: 65449 | N2: 56424 | O2: 71110
A3: EMP1002 | B3: Technology | C3: Data Analyst | D3: Delhi | E3: 78827 | F3: 21621 | G3: 7246 | H3: 4381 | I3: 4402 | J3: 9459 | K3: 6149 | L3: 9459 | M3: 116477 | N3: 100869 | O3: 125936
A4: EMP1003 | B4: Operations | C4: Operations Analyst | D4: Gurugram | E4: 47693 | F4: 10762 | G4: 3114 | H4: 1589 | I4: 4416 | J4: 5723 | K4: 2441 | L4: 5723 | M4: 67574 | N4: 59410 | O4: 73297
A5: EMP1004 | B5: Sales | C5: Business Development Executive | D5: Gurugram | E5: 39494 | F5: 10690 | G5: 2727 | H5: 2046 | I5: 3 | J5: 4739 | K5: 2067 | L5: 4739 | M5: 54960 | N5: 48154 | O5: 59699
A6: EMP1005 | B6: Marketing | C6: Marketing Executive | D6: Gurugram | E6: 49959 | F6: 11661 | G6: 4193 | H6: 2767 | I6: 1347 | J6: 5995 | K6: 2215 | L6: 5995 | M6: 69927 | N6: 61717 | O6: 75922
A7: EMP1006 | B7: Marketing | C7: Marketing Executive | D7: Gurugram | E7: 58303 | F7: 13748 | G7: 4563 | H7: 303 | I7: 1270 | J7: 6996 | K7: 2478 | L7: 6996 | M7: 78187 | N7: 68713 | O7: 85183
A8: EMP1007 | B8: Marketing | C8: Marketing Executive | D8: Gurugram | E8: 51664 | F8: 10065 | G8: 6192 | H8: 1103 | I8: 4883 | J8: 6200 | K8: 3024 | L8: 6200 | M8: 73907 | N8: 64683 | O8: 80107
A9: EMP1008 | B9: Technology | C9: Software Developer | D9: Gurugram | E9: 35392 | F9: 8616 | G9: 3456 | H9: 1503 | I9: 2239 | J9: 4247 | K9: 2497 | L9: 4247 | M9: 51206 | N9: 44462 | O9: 55453
A10: EMP1009 | B10: Sales | C10: Business Development Executive | D10: Delhi | E10: 28202 | F10: 6119 | G10: 1888 | H10: 1812 | I10: 2352 | J10: 3384 | K10: 2922 | L10: 3384 | M10: 40373 | N10: 34067 | O10: 43757
A11: EMP1010 | B11: Operations | C11: Operations Executive | D11: Gurugram | E11: 43087 | F11: 11195 | G11: 2609 | H11: 1752 | I11: 3479 | J11: 5170 | K11: 4072 | L11: 5170 | M11: 62122 | N11: 52880 | O11: 67292
A12: EMP1011 | B12: Marketing | C12: Marketing Executive | D12: Gurugram | E12: 53945 | F12: 12473 | G12: 3553 | H12: 2784 | I12: 872 | J12: 6473 | K12: 4127 | L12: 6473 | M12: 73627 | N12: 63027 | O12: 80100
A13: EMP1012 | B13: Technology | C13: Technology Manager | D13: Gurugram | E13: 107504 | F13: 26615 | G13: 10908 | H13: 1798 | I13: 2707 | J13: 12900 | K13: 8437 | L13: 12900 | M13: 149532 | N13: 128195 | O13: 162432
... A101: EMP1100 | B101: Marketing | C101: Digital Marketing Analyst | D101: Delhi | E101: 77409 | F101: 16515 | G101: 6028 | H101: 3328 | I101: 4599 | J101: 9289 | K101: 4021 | L101: 9289 | M101: 107879 | N101: 94569 | O101: 117168

Sheet Payroll_Calculation
A1: Employee ID | B1: Department | C1: Basic Salary | D1: HRA | E1: Allowances | F1: Incentive | G1: Overtime | H1: Gross Salary | I1: Employee PF | J1: Tax | K1: Net Salary | L1: Employer Contribution | M1: Employer Cost
A2: =Employee_Data!A2 -> EMP1001 | B2: =Employee_Data!B2 -> HR | C2: =Employee_Data!E2 -> 47174 | D2: =Employee_Data!F2 -> 10734 | E2: =Employee_Data!G2 -> 4219 | F2: =Employee_Data!H2 -> 2625 | G2: =Employee_Data!I2 -> 697 | H2: =SUM(C2:G2) -> 65449 | I2: =Employee_Data!J2 -> 5661 | J2: =Employee_Data!K2 -> 3364 | K2: =H2-I2-J2 -> 56424 | L2: =Employee_Data!L2 -> 5661 | M2: =H2+L2 -> 71110
A3: =Employee_Data!A3 -> EMP1002 | B3: =Employee_Data!B3 -> Technology | C3: =Employee_Data!E3 -> 78827 | D3: =Employee_Data!F3 -> 21621 | E3: =Employee_Data!G3 -> 7246 | F3: =Employee_Data!H3 -> 4381 | G3: =Employee_Data!I3 -> 4402 | H3: =SUM(C3:G3) -> 116477 | I3: =Employee_Data!J3 -> 9459 | J3: =Employee_Data!K3 -> 6149 | K3: =H3-I3-J3 -> 100869 | L3: =Employee_Data!L3 -> 9459 | M3: =H3+L3 -> 125936
A4: =Employee_Data!A4 -> EMP1003 | B4: =Employee_Data!B4 -> Operations | C4: =Employee_Data!E4 -> 47693 | D4: =Employee_Data!F4 -> 10762 | E4: =Employee_Data!G4 -> 3114 | F4: =Employee_Data!H4 -> 1589 | G4: =Employee_Data!I4 -> 4416 | H4: =SUM(C4:G4) -> 67574 | I4: =Employee_Data!J4 -> 5723 | J4: =Employee_Data!K4 -> 2441 | K4: =H4-I4-J4 -> 59410 | L4: =Employee_Data!L4 -> 5723 | M4: =H4+L4 -> 73297
A5: =Employee_Data!A5 -> EMP1004 | B5: =Employee_Data!B5 -> Sales | C5: =Employee_Data!E5 -> 39494 | D5: =Employee_Data!F5 -> 10690 | E5: =Employee_Data!G5 -> 2727 | F5: =Employee_Data!H5 -> 2046 | G5: =Employee_Data!I5 -> 3 | H5: =SUM(C5:G5) -> 54960 | I5: =Employee_Data!J5 -> 4739 | J5: =Employee_Data!K5 -> 2067 | K5: =H5-I5-J5 -> 48154 | L5: =Employee_Data!L5 -> 4739 | M5: =H5+L5 -> 59699
A6: =Employee_Data!A6 -> EMP1005 | B6: =Employee_Data!B6 -> Marketing | C6: =Employee_Data!E6 -> 49959 | D6: =Employee_Data!F6 -> 11661 | E6: =Employee_Data!G6 -> 4193 | F6: =Employee_Data!H6 -> 2767 | G6: =Employee_Data!I6 -> 1347 | H6: =SUM(C6:G6) -> 69927 | I6: =Employee_Data!J6 -> 5995 | J6: =Employee_Data!K6 -> 2215 | K6: =H6-I6-J6 -> 61717 | L6: =Employee_Data!L6 -> 5995 | M6: =H6+L6 -> 75922
A7: =Employee_Data!A7 -> EMP1006 | B7: =Employee_Data!B7 -> Marketing | C7: =Employee_Data!E7 -> 58303 | D7: =Employee_Data!F7 -> 13748 | E7: =Employee_Data!G7 -> 4563 | F7: =Employee_Data!H7 -> 303 | G7: =Employee_Data!I7 -> 1270 | H7: =SUM(C7:G7) -> 78187 | I7: =Employee_Data!J7 -> 6996 | J7: =Employee_Data!K7 -> 2478 | K7: =H7-I7-J7 -> 68713 | L7: =Employee_Data!L7 -> 6996 | M7: =H7+L7 -> 85183
A8: =Employee_Data!A8 -> EMP1007 | B8: =Employee_Data!B8 -> Marketing | C8: =Employee_Data!E8 -> 51664 | D8: =Employee_Data!F8 -> 10065 | E8: =Employee_Data!G8 -> 6192 | F8: =Employee_Data!H8 -> 1103 | G8: =Employee_Data!I8 -> 4883 | H8: =SUM(C8:G8) -> 73907 | I8: =Employee_Data!J8 -> 6200 | J8: =Employee_Data!K8 -> 3024 | K8: =H8-I8-J8 -> 64683 | L8: =Employee_Data!L8 -> 6200 | M8: =H8+L8 -> 80107
A9: =Employee_Data!A9 -> EMP1008 | B9: =Employee_Data!B9 -> Technology | C9: =Employee_Data!E9 -> 35392 | D9: =Employee_Data!F9 -> 8616 | E9: =Employee_Data!G9 -> 3456 | F9: =Employee_Data!H9 -> 1503 | G9: =Employee_Data!I9 -> 2239 | H9: =SUM(C9:G9) -> 51206 | I9: =Employee_Data!J9 -> 4247 | J9: =Employee_Data!K9 -> 2497 | K9: =H9-I9-J9 -> 44462 | L9: =Employee_Data!L9 -> 4247 | M9: =H9+L9 -> 55453
A10: =Employee_Data!A10 -> EMP1009 | B10: =Employee_Data!B10 -> Sales | C10: =Employee_Data!E10 -> 28202 | D10: =Employee_Data!F10 -> 6119 | E10: =Employee_Data!G10 -> 1888 | F10: =Employee_Data!H10 -> 1812 | G10: =Employee_Data!I10 -> 2352 | H10: =SUM(C10:G10) -> 40373 | I10: =Employee_Data!J10 -> 3384 | J10: =Employee_Data!K10 -> 2922 | K10: =H10-I10-J10 -> 34067 | L10: =Employee_Data!L10 -> 3384 | M10: =H10+L10 -> 43757
A11: =Employee_Data!A11 -> EMP1010 | B11: =Employee_Data!B11 -> Operations | C11: =Employee_Data!E11 -> 43087 | D11: =Employee_Data!F11 -> 11195 | E11: =Employee_Data!G11 -> 2609 | F11: =Employee_Data!H11 -> 1752 | G11: =Employee_Data!I11 -> 3479 | H11: =SUM(C11:G11) -> 62122 | I11: =Employee_Data!J11 -> 5170 | J11: =Employee_Data!K11 -> 4072 | K11: =H11-I11-J11 -> 52880 | L11: =Employee_Data!L11 -> 5170 | M11: =H11+L11 -> 67292
A12: =Employee_Data!A12 -> EMP1011 | B12: =Employee_Data!B12 -> Marketing | C12: =Employee_Data!E12 -> 53945 | D12: =Employee_Data!F12 -> 12473 | E12: =Employee_Data!G12 -> 3553 | F12: =Employee_Data!H12 -> 2784 | G12: =Employee_Data!I12 -> 872 | H12: =SUM(C12:G12) -> 73627 | I12: =Employee_Data!J12 -> 6473 | J12: =Employee_Data!K12 -> 4127 | K12: =H12-I12-J12 -> 63027 | L12: =Employee_Data!L12 -> 6473 | M12: =H12+L12 -> 80100
A13: =Employee_Data!A13 -> EMP1012 | B13: =Employee_Data!B13 -> Technology | C13: =Employee_Data!E13 -> 107504 | D13: =Employee_Data!F13 -> 26615 | E13: =Employee_Data!G13 -> 10908 | F13: =Employee_Data!H13 -> 1798 | G13: =Employee_Data!I13 -> 2707 | H13: =SUM(C13:G13) -> 149532 | I13: =Employee_Data!J13 -> 12900 | J13: =Employee_Data!K13 -> 8437 | K13: =H13-I13-J13 -> 128195 | L13: =Employee_Data!L13 -> 12900 | M13: =H13+L13 -> 162432
... A101: =Employee_Data!A101 -> EMP1100 | B101: =Employee_Data!B101 -> Marketing | C101: =Employee_Data!E101 -> 77409 | D101: =Employee_Data!F101 -> 16515 | E101: =Employee_Data!G101 -> 6028 | F101: =Employee_Data!H101 -> 3328 | G101: =Employee_Data!I101 -> 4599 | H101: =SUM(C101:G101) -> 107879 | I101: =Employee_Data!J101 -> 9289 | J101: =Employee_Data!K101 -> 4021 | K101: =H101-I101-J101 -> 94569 | L101: =Employee_Data!L101 -> 9289 | M101: =H101+L101 -> 117168

Sheet Department_Cost_Analysis
B2: Department | C2: Headcount | D2: Gross Salary | E2: Overtime | F2: Incentives | G2: Employer Cost | H2: Cost / Employee | I2: % Total Cost
B3: Marketing | C3: =COUNTIF(Payroll_Calculation!$B$2:$B$101,B3) -> 28 | D3: =SUMIF(Payroll_Calculation!$B$2:$B$101,B3,Payroll_Calculation!$H$2:$H$101) -> 2276661 | E3: =SUMIF(Payroll_Calculation!$B$2:$B$101,B3,Payroll_Calculation!$G$2:$G$101) -> 64060 | F3: =SUMIF(Payroll_Calculation!$B$2:$B$101,B3,Payroll_Calculation!$F$2:$F$101) -> 55335 | G3: =SUMIF(Payroll_Calculation!$B$2:$B$101,B3,Payroll_Calculation!$M$2:$M$101) -> 2474260 | H3: =G3/C3 -> 88366.429 | I3: =G3/$G$9 -> 0.28536433
B4: Finance | C4: =COUNTIF(Payroll_Calculation!$B$2:$B$101,B4) -> 10 | D4: =SUMIF(Payroll_Calculation!$B$2:$B$101,B4,Payroll_Calculation!$H$2:$H$101) -> 834381 | E4: =SUMIF(Payroll_Calculation!$B$2:$B$101,B4,Payroll_Calculation!$G$2:$G$101) -> 29969 | F4: =SUMIF(Payroll_Calculation!$B$2:$B$101,B4,Payroll_Calculation!$F$2:$F$101) -> 26603 | G4: =SUMIF(Payroll_Calculation!$B$2:$B$101,B4,Payroll_Calculation!$M$2:$M$101) -> 905982 | H4: =G4/C4 -> 90598.2 | I4: =G4/$G$9 -> 0.10448981
B5: HR | C5: =COUNTIF(Payroll_Calculation!$B$2:$B$101,B5) -> 8 | D5: =SUMIF(Payroll_Calculation!$B$2:$B$101,B5,Payroll_Calculation!$H$2:$H$101) -> 574730 | E5: =SUMIF(Payroll_Calculation!$B$2:$B$101,B5,Payroll_Calculation!$G$2:$G$101) -> 21312 | F5: =SUMIF(Payroll_Calculation!$B$2:$B$101,B5,Payroll_Calculation!$F$2:$F$101) -> 17265 | G5: =SUMIF(Payroll_Calculation!$B$2:$B$101,B5,Payroll_Calculation!$M$2:$M$101) -> 623999 | H5: =G5/C5 -> 77999.875 | I5: =G5/$G$9 -> 0.071967804
B6: Sales | C6: =COUNTIF(Payroll_Calculation!$B$2:$B$101,B6) -> 22 | D6: =SUMIF(Payroll_Calculation!$B$2:$B$101,B6,Payroll_Calculation!$H$2:$H$101) -> 1548233 | E6: =SUMIF(Payroll_Calculation!$B$2:$B$101,B6,Payroll_Calculation!$G$2:$G$101) -> 55248 | F6: =SUMIF(Payroll_Calculation!$B$2:$B$101,B6,Payroll_Calculation!$F$2:$F$101) -> 43164 | G6: =SUMIF(Payroll_Calculation!$B$2:$B$101,B6,Payroll_Calculation!$M$2:$M$101) -> 1679905 | H6: =G6/C6 -> 76359.318 | I6: =G6/$G$9 -> 0.19374883
B7: Operations | C7: =COUNTIF(Payroll_Calculation!$B$2:$B$101,B7) -> 19 | D7: =SUMIF(Payroll_Calculation!$B$2:$B$101,B7,Payroll_Calculation!$H$2:$H$101) -> 1564593 | E7: =SUMIF(Payroll_Calculation!$B$2:$B$101,B7,Payroll_Calculation!$G$2:$G$101) -> 50640 | F7: =SUMIF(Payroll_Calculation!$B$2:$B$101,B7,Payroll_Calculation!$F$2:$F$101) -> 37393 | G7: =SUMIF(Payroll_Calculation!$B$2:$B$101,B7,Payroll_Calculation!$M$2:$M$101) -> 1698773 | H7: =G7/C7 -> 89409.105 | I7: =G7/$G$9 -> 0.19592493
B8: Technology | C8: =COUNTIF(Payroll_Calculation!$B$2:$B$101,B8) -> 13 | D8: =SUMIF(Payroll_Calculation!$B$2:$B$101,B8,Payroll_Calculation!$H$2:$H$101) -> 1187004 | E8: =SUMIF(Payroll_Calculation!$B$2:$B$101,B8,Payroll_Calculation!$G$2:$G$101) -> 36439 | F8: =SUMIF(Payroll_Calculation!$B$2:$B$101,B8,Payroll_Calculation!$F$2:$F$101) -> 29992 | G8: =SUMIF(Payroll_Calculation!$B$2:$B$101,B8,Payroll_Calculation!$M$2:$M$101) -> 1287611 | H8: =G8/C8 -> 99047 | I8: =G8/$G$9 -> 0.1485043
B9: TOTAL | C9: =SUM(C3:C8) -> 100 | D9: =SUM(D3:D8) -> 7985602 | E9: =SUM(E3:E8) -> 257668 | F9: =SUM(F3:F8) -> 209752 | G9: =SUM(G3:G8) -> 8670530 | H9: =G9/C9 -> 86705.3 | I9: =SUM(I3:I8) -> 1

Sheet Budget_vs_Actual
B2: Department | C2: Budgeted Employer Cost | D2: Actual Employer Cost | E2: Variance | F2: Variance % | G2: Status
B3: Marketing | C3: 2470500 | D3: 2474260 | E3: 3760 | F3: 0.002 | G3: Unfavourable
B4: Finance | C4: 936300 | D4: 905982 | E4: -30318 | F4: -0.032 | G4: Favourable
B5: HR | C5: 628300 | D5: 623999 | E5: -4301 | F5: -0.007 | G5: Favourable
B6: Sales | C6: 1617100 | D6: 1679905 | E6: 62805 | F6: 0.039 | G6: Unfavourable
B7: Operations | C7: 1754900 | D7: 1698773 | E7: -56127 | F7: -0.032 | G7: Favourable
B8: Technology | C8: 1261700 | D8: 1287611 | E8: 25911 | F8: 0.021 | G8: Unfavourable
B9: TOTAL | C9: 8668800 | D9: 8670530 | E9: 1730 | F9: 0 | G9: Slightly Unfavourable

Sheet Scenario_Analysis
B2: Scenario | C2: Assumption | D2: Monthly Employer Cost | E2: Monthly Impact | F2: Annual Employer Cost | G2: Annual Impact
B3: Current Workforce | C3: Existing workforce | D3: 8670530 | E3: 0 | F3: 104046360 | G3: 0
B4: Hiring +10 | C4: 10 additional hires at current average employer cost | D4: 9537583 | E4: 867053 | F4: 114450996 | G4: 10404636
B5: Salary Revision +8% | C5: 8% increase in salary-linked components | D5: 9364172 | E5: 693642 | F5: 112370064 | G5: 8323704
B6: Overtime -20% | C6: 20% reduction in overtime cost | D6: 8618996 | E6: -51534 | F6: 103427952 | G6: -618408

Sheet Dashboard
B2: PAYROLL & EMPLOYEE COST DASHBOARD
B4: Total Employees | D4: Departments | F4: Monthly Employer Cost | H4: Average Cost / Employee
B5: =COUNTA(Employee_Data!A2:A101) -> 100 | D5: =COUNTA(Department_Cost_Analysis!B3:B8) -> 6 | F5: =SUM(Payroll_Calculation!M2:M101) -> 8670530 | H5: =AVERAGE(Payroll_Calculation!M2:M101) -> 86705.3
B7: Overtime Cost | D7: Incentive Cost | F7: Annual Employer Cost | H7: Highest-Cost Department
B8: =SUM(Payroll_Calculation!G2:G101) -> 257668 | D8: =SUM(Payroll_Calculation!F2:F101) -> 209752 | F8: =SUM(Payroll_Calculation!M2:M101)*12 -> 104046360 | H8: =INDEX(Department_Cost_Analysis!B3:B8,MATCH(MAX(Department_Cost_Analysis!G3:G8),Department_Cost_Analysis!G3:G8,0)) -> Marketing

Sheet Management_Insights
B2: MANAGEMENT INSIGHTS
B5: 1. | C5: Identify the department with the highest total employer cost and assess whether headcount or compensation mix is the main driver.
B6: 2. | C6: Review Budget vs. Actual variances and investigate departments with unfavourable employee-cost variances.
B7: 3. | C7: Use the hiring scenario to estimate incremental annual employee cost before adding new employees.
B8: 4. | C8: Use the salary-revision scenario to quantify the financial effect of compensation changes.
B9: 5. | C9: Use the overtime scenario to estimate potential savings from reducing overtime expenditure.
B10: 6. | C10: Monitor cost per employee alongside headcount to distinguish workforce growth from compensation-driven cost increases.
